fsinfo/__init__.py
fsinfo/directoryinfo.py
fsinfo/fileinfo.py
fsinfo/filesysteminfo.py
fsinfo-0.0.8.dist-info/LICENSE
fsinfo-0.0.8.dist-info/METADATA
fsinfo-0.0.8.dist-info/WHEEL
fsinfo-0.0.8.dist-info/top_level.txt
fsinfo-0.0.8.dist-info/RECORD
