Metadata-Version: 2.1
Name: fsinfo
Version: 0.0.8
Summary: A Python library for cross-platform filesystem operations, providing classes for handling files and directories.
Home-page: https://github.com/KarelOmab/fsinfo
Author: Karel Tutsu
Author-email: karel.tutsu@gmail.com
Classifier: Programming Language :: Python :: 3
Classifier: License :: OSI Approved :: MIT License
Classifier: Operating System :: OS Independent
Requires-Python: >=3.6
License-File: LICENSE
